chaostoolkit-1.18.0.dist-info/METADATA
chaostoolkit-1.18.0.dist-info/WHEEL
chaostoolkit-1.18.0.dist-info/entry_points.txt
chaostoolkit-1.18.0.dist-info/licenses/LICENSE
chaostoolkit/__init__.py
chaostoolkit/__main__.py
chaostoolkit/check.py
chaostoolkit/cli.py
chaostoolkit/logging.py
chaostoolkit-1.18.0.dist-info/RECORD
