Metadata-Version: 2.1
Name: chaostoolkit
Version: 1.18.0
Summary: Chaos Engineering Toolkit for everyone
Author-Email: Chaos Toolkit <contact@chaostoolkit.org>, Sylvain Hellegouarch <sh@defuze.org>
License: Apache-2.0
Classifier: Development Status :: 5 - Production/Stable
Classifier: Intended Audience :: Developers
Classifier: License :: Freely Distributable
Classifier: License :: OSI Approved :: Apache Software License
Classifier: Operating System :: OS Independent
Classifier: Programming Language :: Python
Classifier: Programming Language :: Python :: 3
Classifier: Programming Language :: Python :: 3.8
Classifier: Programming Language :: Python :: 3.9
Classifier: Programming Language :: Python :: 3.10
Classifier: Programming Language :: Python :: 3.11
Classifier: Programming Language :: Python :: 3.12
Classifier: Programming Language :: Python :: Implementation
Classifier: Programming Language :: Python :: Implementation :: CPython
Project-URL: Homepage, https://chaostoolkit.org/
Project-URL: Repository, https://github.com/chaostoolkit/chaostoolkit
Project-URL: Documentation, https://chaostoolkit.org/reference/concepts/
Project-URL: Changelog, https://github.com/chaostoolkit/chaostoolkit/blob/main/CHANGELOG.md
Requires-Python: >=3.8
Requires-Dist: click>=8.0
Requires-Dist: click-plugins>=1.1
Requires-Dist: logzero>=1.5.0
Requires-Dist: chaostoolkit-lib>=1.33
Requires-Dist: requests>=2.28
Requires-Dist: python-json-logger>=2.0
Requires-Dist: pyyaml>=6.0
Requires-Dist: importlib-metadata>=6.0
